[
    {
        "id": "12345",
        "titulo": "Airport Project",
        "area_enfoque": "Minera",
        "docente_codigo": "67",
        "estudiantes": [
            "John Smith",
            "Emily Johnson",
            "Michael Davis"
        ],
        "estado": "Aprobada",
        "fecha_creacion": "2023/05/23",
        "estudiante_codigo": "0912",
        "documento_idea": "67890",
        "observacion": "Lorem ipsum dolor sit amet, consectetur adipiscing elit. Cras in semper magna. Suspendisse mattis neque id nunc commodo, ut interdum odio dictum. Curabitur facilisis eros vitae iaculis auctor. Ut sit amet dictum enim. Aenean ut lacus et turpis tristique ornare. Donec eu feugiat nunc."
    },
    {
        "id": "55555",
        "titulo": "Space Exploration",
        "area_enfoque": "Comercial",
        "docente_codigo": "18",
        "estudiantes": [
            "Robert Johnson",
            "Sophia Anderson",
            "David Thompson"
        ],
        "estado": "Vencida",
        "fecha_creacion": "2023/05/24",
        "estudiante_codigo": "0827",
        "documento_idea": "13579",
        "observacion": "Lorem ipsum dolor sit amet, consectetur adipiscing elit. Cras in semper magna. Suspendisse mattis neque id nunc commodo, ut interdum odio dictum. Curabitur facilisis eros vitae iaculis auctor. Ut sit amet dictum enim. Aenean ut lacus et turpis tristique ornare. Donec eu feugiat nunc."
    },
    {
        "id": "99999",
        "titulo": "Mobile App Development",
        "area_enfoque": "Industrial",
        "docente_codigo": "76",
        "estudiantes": [
            "Sarah Thompson",
            "Jacob Lee",
            "Megan Davis"
        ],
        "estado": "Pendiente",
        "fecha_creacion": "2023/05/19",
        "estudiante_codigo": "0123",
        "documento_idea": "75309",
        "observacion": "Lorem ipsum dolor sit amet, consectetur adipiscing elit. Cras in semper magna. Suspendisse mattis neque id nunc commodo, ut interdum odio dictum. Curabitur facilisis eros vitae iaculis auctor. Ut sit amet dictum enim. Aenean ut lacus et turpis tristique ornare. Donec eu feugiat nunc."
    }
]